{"cameraMode":{"drawMode":0,"name":"Shaded","section":"Shading Mode"},"sceneLighting":true,"audioPlay":false,"sceneViewState":{"showFog":true,"showMaterialUpdate":false,"showSkybox":true,"showFlares":true,"showImageEffects":true,"showParticleSystems":true},"in2DMode":false,"pivot":{"x":144.9171905517578,"y":-22.430025100708009,"z":53.016761779785159},"rotation":{"x":-0.15511445701122285,"y":-0.3474069833755493,"z":0.05836699530482292,"w":-0.92295241355896},"size":0.2857913076877594,"orthographic":false}